django_minio_storage_py_pa-0.0.2.dist-info/DESCRIPTION.rst
django_minio_storage_py_pa-0.0.2.dist-info/METADATA
django_minio_storage_py_pa-0.0.2.dist-info/RECORD
django_minio_storage_py_pa-0.0.2.dist-info/WHEEL
django_minio_storage_py_pa-0.0.2.dist-info/metadata.json
django_minio_storage_py_pa-0.0.2.dist-info/top_level.txt
minio_storage/__init__.py
minio_storage/files.py
minio_storage/storage.py
