Metadata-Version: 2.0
Name: django-minio-storage-py-pa
Version: 0.0.2
Summary: Django file storage using the minio python client
Home-page: https://github.com/py-pa/django-minio-storage
Author: Tom Houlé
Author-email: tom@kafunsho.be
License: MIT
Platform: UNKNOWN
Classifier: Development Status :: 4 - Beta
Classifier: Environment :: Web Environment
Classifier: Intended Audience :: Developers
Classifier: License :: OSI Approved :: BSD License
Classifier: Operating System :: OS Independent
Classifier: Programming Language :: Python
Classifier: Programming Language :: Python :: 3.3
Classifier: Programming Language :: Python :: 3.4
Classifier: Programming Language :: Python :: 3.5
Classifier: Programming Language :: Python :: 3.6
Classifier: Framework :: Django
Requires-Dist: django (>=1.8)
Requires-Dist: minio (>=2.2.2)
Provides-Extra: test
Requires-Dist: coverage; extra == 'test'
Requires-Dist: requests; extra == 'test'
